{"cameraMode":{"drawMode":0,"name":"Shaded","section":"Shading Mode"},"sceneLighting":false,"audioPlay":false,"sceneViewState":{"showFog":true,"showMaterialUpdate":false,"showSkybox":false,"showFlares":true,"showImageEffects":true,"showParticleSystems":true},"in2DMode":false,"pivot":{"x":-6.955190658569336,"y":0.048307836055755618,"z":15.035374641418457},"rotation":{"x":-0.6730360984802246,"y":-0.0028872336260974409,"z":0.00262651639059186,"w":-0.7396041750907898},"size":4.992221355438232,"orthographic":false}